cdklabs/cdk_validator_cfnguard/__init__.py
cdklabs/cdk_validator_cfnguard/py.typed
cdklabs/cdk_validator_cfnguard/_jsii/__init__.py
cdklabs/cdk_validator_cfnguard/_jsii/cdk-validator-cfnguard@0.0.60.jsii.tgz
cdklabs.cdk_validator_cfnguard-0.0.60.dist-info/LICENSE
cdklabs.cdk_validator_cfnguard-0.0.60.dist-info/METADATA
cdklabs.cdk_validator_cfnguard-0.0.60.dist-info/WHEEL
cdklabs.cdk_validator_cfnguard-0.0.60.dist-info/top_level.txt
cdklabs.cdk_validator_cfnguard-0.0.60.dist-info/RECORD
